{
  "id": "009Os",
  "image_path": "puzzles\\plain_boards\\009Os.png",
  "input_annotation_json_path": "puzzles\\annotations_json\\009Os.json",
  "side_to_move": "white",
  "fen": "r2b2k1/1p3q1p/p2p4/3P2p1/2P1PRQr/8/P2B3P/2R4K w - - 1 29",
  "model": "google/gemma-4-31b-it",
  "my_pieces": [
    {
      "square": "d5",
      "piece": "P"
    },
    {
      "square": "c4",
      "piece": "P"
    },
    {
      "square": "e4",
      "piece": "P"
    },
    {
      "square": "f4",
      "piece": "R"
    },
    {
      "square": "g4",
      "piece": "Q"
    },
    {
      "square": "a2",
      "piece": "P"
    },
    {
      "square": "d2",
      "piece": "B"
    },
    {
      "square": "h2",
      "piece": "P"
    },
    {
      "square": "c1",
      "piece": "R"
    },
    {
      "square": "h1",
      "piece": "K"
    }
  ],
  "opponent_pieces": [
    {
      "square": "a8",
      "piece": "r"
    },
    {
      "square": "d8",
      "piece": "b"
    },
    {
      "square": "g8",
      "piece": "k"
    },
    {
      "square": "b7",
      "piece": "p"
    },
    {
      "square": "f7",
      "piece": "q"
    },
    {
      "square": "h7",
      "piece": "p"
    },
    {
      "square": "a6",
      "piece": "p"
    },
    {
      "square": "d6",
      "piece": "p"
    },
    {
      "square": "g5",
      "piece": "p"
    },
    {
      "square": "h4",
      "piece": "r"
    }
  ],
  "valid_my_pieces": [
    {
      "square": "d5",
      "piece": "P"
    },
    {
      "square": "c4",
      "piece": "P"
    },
    {
      "square": "e4",
      "piece": "P"
    },
    {
      "square": "f4",
      "piece": "R"
    },
    {
      "square": "g4",
      "piece": "Q"
    },
    {
      "square": "a2",
      "piece": "P"
    },
    {
      "square": "d2",
      "piece": "B"
    },
    {
      "square": "h2",
      "piece": "P"
    },
    {
      "square": "c1",
      "piece": "R"
    },
    {
      "square": "h1",
      "piece": "K"
    }
  ],
  "invalid_my_pieces": [],
  "valid_opponent_pieces": [
    {
      "square": "a8",
      "piece": "r"
    },
    {
      "square": "d8",
      "piece": "b"
    },
    {
      "square": "g8",
      "piece": "k"
    },
    {
      "square": "b7",
      "piece": "p"
    },
    {
      "square": "f7",
      "piece": "q"
    },
    {
      "square": "h7",
      "piece": "p"
    },
    {
      "square": "a6",
      "piece": "p"
    },
    {
      "square": "d6",
      "piece": "p"
    },
    {
      "square": "g5",
      "piece": "p"
    },
    {
      "square": "h4",
      "piece": "r"
    }
  ],
  "invalid_opponent_pieces": [],
  "candidate_move_arrows": [
    {
      "from": "f4",
      "to": "h4",
      "piece": "R"
    },
    {
      "from": "g4",
      "to": "g5",
      "piece": "Q"
    }
  ],
  "valid_candidate_move_arrows": [
    {
      "from": "g4",
      "to": "g5",
      "piece": "Q"
    }
  ],
  "invalid_candidate_move_arrows": [
    {
      "from": "f4",
      "to": "h4",
      "piece": "R",
      "reason": "illegal_move"
    }
  ],
  "threat_arrows": [
    {
      "from": "h4",
      "to": "g4",
      "piece": "r"
    },
    {
      "from": "f7",
      "to": "f4",
      "piece": "q"
    }
  ],
  "valid_threat_arrows": [
    {
      "from": "h4",
      "to": "g4",
      "piece": "r"
    },
    {
      "from": "f7",
      "to": "f4",
      "piece": "q"
    }
  ],
  "invalid_threat_arrows": [],
  "key_squares": [
    "h4",
    "g5",
    "f4"
  ],
  "debug_png": "puzzles\\gemma-4-31b-it\\model_arrows_fen\\annotated_boards_debug\\009Os.png",
  "final_png": "puzzles\\gemma-4-31b-it\\model_arrows_fen\\annotated_boards_final\\009Os.png"
}