{
  "id": "009uB",
  "image_path": "puzzles\\random\\annotated_boards\\009uB.png",
  "input_annotation_json_path": "puzzles\\random\\annotations_json\\009uB.json",
  "side_to_move": "black",
  "fen": "3br2r/5k1p/4p1pQ/P5P1/1B5P/P6q/5R2/6K1 b - - 1 35",
  "model": "google/gemma-4-31b-it",
  "baseline_type": "gold_annotated_image_to_moves",
  "move_data": {
    "candidate_moves": [
      "g4g4",
      "f2f2",
      "h8f8",
      "e8e7",
      "d8c7"
    ],
    "valid_candidate_moves": [],
    "invalid_candidate_moves": [
      {
        "move": "g4g4",
        "reason": "invalid_uci"
      },
      {
        "move": "f2f2",
        "reason": "invalid_uci"
      },
      {
        "move": "h8f8",
        "reason": "illegal_move"
      },
      {
        "move": "e8e7",
        "reason": "illegal_move"
      },
      {
        "move": "d8c7",
        "reason": "illegal_move"
      }
    ]
  }
}