{
  "id": "00Hpe",
  "input_annotation_json_path": "puzzles\\annotations_json\\00Hpe.json",
  "side_to_move": "black",
  "fen": "1rr3k1/4Qppp/qp2p3/P2pn3/3N4/4P2P/5PP1/RR4K1 b - - 3 29",
  "model": "random",
  "baseline_type": "random_baseline",
  "baseline_seed": "12345:00Hpe",
  "candidate_move_arrows": [
    {
      "from": "c8",
      "to": "c6",
      "piece": "r"
    },
    {
      "from": "e5",
      "to": "c4",
      "piece": "n"
    },
    {
      "from": "e5",
      "to": "d7",
      "piece": "n"
    }
  ],
  "threat_arrows": [
    {
      "from": "e7",
      "to": "f6",
      "piece": "Q"
    },
    {
      "from": "a5",
      "to": "b6",
      "piece": "P"
    },
    {
      "from": "e3",
      "to": "d4",
      "piece": "P"
    }
  ],
  "key_squares": [
    "f7",
    "c3",
    "f8"
  ],
  "annotation_bundle": {
    "arrows": [
      {
        "from_square": "c8",
        "to_square": "c6",
        "kind": "candidate_move",
        "color": "#1e88e5"
      },
      {
        "from_square": "e5",
        "to_square": "c4",
        "kind": "candidate_move",
        "color": "#1e88e5"
      },
      {
        "from_square": "e5",
        "to_square": "d7",
        "kind": "candidate_move",
        "color": "#1e88e5"
      },
      {
        "from_square": "e7",
        "to_square": "f6",
        "kind": "threat",
        "color": "#c62828"
      },
      {
        "from_square": "a5",
        "to_square": "b6",
        "kind": "threat",
        "color": "#c62828"
      },
      {
        "from_square": "e3",
        "to_square": "d4",
        "kind": "threat",
        "color": "#c62828"
      }
    ],
    "highlighted_squares": [
      {
        "square": "f7",
        "kind": "key_square",
        "color": "#42a5f566"
      },
      {
        "square": "c3",
        "kind": "key_square",
        "color": "#42a5f566"
      },
      {
        "square": "f8",
        "kind": "key_square",
        "color": "#42a5f566"
      }
    ]
  },
  "final_png": "puzzles\\random\\annotated_boards\\00Hpe.png"
}