{
  "id": "002LW_annotated",
  "image_path": "puzzles\\annotated_boards\\002LW_annotated.png",
  "input_annotation_json_path": "puzzles\\annotations_json\\002LW.json",
  "side_to_move": "black",
  "fen": "3r1rk1/1b1n1pp1/3p4/p4PPQ/4P3/3q1BN1/8/2R2RK1 b - - 1 28",
  "model": "google/gemma-4-31b-it",
  "baseline_type": "gold_annotated_image_to_moves",
  "move_data": {
    "candidate_moves": [
      "f3f3",
      "d7e5",
      "b7a6",
      "d7c5",
      "d8d4"
    ],
    "valid_candidate_moves": [
      "d7e5",
      "b7a6",
      "d7c5"
    ],
    "invalid_candidate_moves": [
      {
        "move": "f3f3",
        "reason": "invalid_uci"
      },
      {
        "move": "d8d4",
        "reason": "illegal_move"
      }
    ]
  }
}