{
  "id": "009IO_annotated",
  "image_path": "puzzles\\annotated_boards\\009IO_annotated.png",
  "input_annotation_json_path": "puzzles\\annotations_json\\009IO.json",
  "side_to_move": "black",
  "fen": "3rk3/5p1r/p2Np1p1/3bP3/P2n4/8/1P3RPP/5RK1 b - - 4 25",
  "model": "google/gemma-4-31b-it",
  "baseline_type": "gold_annotated_image_to_moves",
  "move_data": {
    "candidate_moves": [
      "c2d4",
      "h7f7",
      "d4c6",
      "d4e2",
      "d4b3"
    ],
    "valid_candidate_moves": [],
    "invalid_candidate_moves": [
      {
        "move": "c2d4",
        "reason": "illegal_move"
      },
      {
        "move": "h7f7",
        "reason": "illegal_move"
      },
      {
        "move": "d4c6",
        "reason": "illegal_move"
      },
      {
        "move": "d4e2",
        "reason": "illegal_move"
      },
      {
        "move": "d4b3",
        "reason": "illegal_move"
      }
    ]
  }
}